grape2spectrogram/__init__.py
grape2spectrogram/eclipse_calc.py
grape2spectrogram/reader.py
grape2spectrogram/solarContext.py
grape2spectrogram/spectrogram.py
grape2spectrogram-5.1.2.dist-info/METADATA
grape2spectrogram-5.1.2.dist-info/WHEEL
grape2spectrogram-5.1.2.dist-info/entry_points.txt
grape2spectrogram-5.1.2.dist-info/RECORD
